coreason_council/__init__.py
coreason_council/core/__init__.py
coreason_council/core/aggregator.py
coreason_council/core/budget.py
coreason_council/core/council_service.py
coreason_council/core/dissenter.py
coreason_council/core/llm_aggregator.py
coreason_council/core/llm_client.py
coreason_council/core/llm_proposer.py
coreason_council/core/models/__init__.py
coreason_council/core/models/interaction.py
coreason_council/core/models/persona.py
coreason_council/core/models/plan.py
coreason_council/core/models/trace.py
coreason_council/core/models/verdict.py
coreason_council/core/panel_selector.py
coreason_council/core/proposer.py
coreason_council/core/speaker.py
coreason_council/main.py
coreason_council/policies.py
coreason_council/resources/presets.yaml
coreason_council/reviewer.py
coreason_council/server.py
coreason_council/settings.py
coreason_council/utils/__init__.py
coreason_council/utils/logger.py
coreason_council-0.6.0.dist-info/METADATA
coreason_council-0.6.0.dist-info/WHEEL
coreason_council-0.6.0.dist-info/entry_points.txt
coreason_council-0.6.0.dist-info/licenses/LICENSE
coreason_council-0.6.0.dist-info/licenses/NOTICE
coreason_council-0.6.0.dist-info/RECORD
