Metadata-Version: 2.4
Name: coreason_council
Version: 0.6.0
Summary: the senate
License: # The Prosperity Public License 3.0.0
License-File: LICENSE
License-File: NOTICE
Author: Gowtham A Rao
Author-email: gowtham.rao@coreason.ai
Requires-Python: >=3.11
Classifier: License :: Other/Proprietary License
Classifier: Programming Language :: Python :: 3.12
Classifier: Operating System :: OS Independent
Requires-Dist: anyio (>=4.12.1,<5.0.0)
Requires-Dist: click (>=8.3.1,<9.0.0)
Requires-Dist: coreason-identity (>=0.1.0,<0.2.0)
Requires-Dist: fastapi (>=0.127.0,<0.128.0)
Requires-Dist: httpx (>=0.28.1,<0.29.0)
Requires-Dist: loguru (>=0.7.3,<0.8.0)
Requires-Dist: pydantic (>=2.12.5,<3.0.0)
Requires-Dist: pydantic-settings (>=2.12.0,<3.0.0)
Requires-Dist: pyyaml (>=6.0.3,<7.0.0)
Requires-Dist: typer (>=0.21.1,<0.22.0)
Requires-Dist: uvicorn[standard] (>=0.40.0,<0.41.0)
Project-URL: Documentation, https://github.com/CoReason-AI/coreason_council
Project-URL: Homepage, https://github.com/CoReason-AI/coreason_council
Project-URL: Repository, https://github.com/CoReason-AI/coreason_council
